model_hub/__init__ 2.py
model_hub/__init__.py
model_hub/__version__ 2.py
model_hub/__version__.py
model_hub/py.typed
model_hub/utils 2.py
model_hub/utils.py
model_hub/huggingface/__init__.py
model_hub/huggingface/_config_parser.py
model_hub/huggingface/_trial.py
model_hub/huggingface/_utils.py
model_hub/mmdetection/__init__.py
model_hub/mmdetection/_callbacks.py
model_hub/mmdetection/_data.py
model_hub/mmdetection/_data_backends.py
model_hub/mmdetection/_trial.py
model_hub/mmdetection/utils.py
model_hub-0.36.0.dist-info/METADATA
model_hub-0.36.0.dist-info/WHEEL
model_hub-0.36.0.dist-info/top_level.txt
model_hub-0.36.0.dist-info/RECORD
