Metadata-Version: 2.1
Name: model-hub
Version: 0.36.0
Summary: Model Hub for Determined Deep Learning Training Platform
Home-page: https://determined.ai/
Author: Determined AI
Author-email: ai-open-source@hpe.com
License: Apache License 2.0
Classifier: License :: OSI Approved :: Apache Software License
Requires-Python: >=3.6
Requires-Dist: determined>=0.13.11
